[
    {
        "source_file": "LINE_ALBUM_貼磚工程_260117_1.jpg",
        "category": "tiling",
        "target_path": "assets/images/projects/tiling/bathroom-tiling-renovation-project.webp",
        "title": "浴室磁磚全室翻新",
        "service_category_text": "貼磚工程",
        "location": "台南市區",
        "completion_date": "2025",
        "seo_alt": "台南浴室磁磚翻新實績 - 防水打底與精密對縫",
        "action": "process"
    },
    {
        "source_file": "LINE_ALBUM_貼磚工程_260117_2.jpg",
        "category": "tiling",
        "target_path": "assets/images/projects/tiling/wall-tiling-installation-technique.webp",
        "title": "牆面磁磚鋪貼工藝",
        "service_category_text": "貼磚工程",
        "location": "永康區",
        "completion_date": "2024",
        "seo_alt": "牆面磁磚薄漿工法與雷射水平校準施工照",
        "action": "process"
    },
    {
        "source_file": "LINE_ALBUM_貼磚工程_260117_3.jpg",
        "category": "tiling",
        "target_path": "assets/images/projects/tiling/floor-tiling-drainage-slope-leveling.webp",
        "title": "地坪洩水坡度調整",
        "service_category_text": "貼磚工程",
        "location": "新化區",
        "completion_date": "2024",
        "seo_alt": "浴室地坪磁磚洩水坡度調整施工實錄",
        "action": "process"
    },
    {
        "source_file": "LINE_ALBUM_貼磚工程_260117_4.jpg",
        "category": "tiling",
        "target_path": "assets/images/projects/tiling/tiling-corner-detail-closeup.webp",
        "title": "磁磚細節展示",
        "service_category_text": "貼磚工程",
        "location": "台南市區",
        "completion_date": "2025",
        "seo_alt": "磁磚職人收邊細節近拍展示",
        "action": "process"
    },
    {
        "source_file": "LINE_20260116_120925.jpg",
        "category": "misc",
        "target_path": "assets/images/projects/misc/misc-home-repair-snapshot.webp",
        "title": "未分類項目",
        "service_category_text": "居家修繕",
        "location": "台南市區",
        "completion_date": "2026",
        "seo_alt": "台南居家修繕施工紀錄",
        "action": "process"
    }
]